streamndr/__init__.py
streamndr/__version__.py
streamndr/metrics/__init__.py
streamndr/metrics/cer.py
streamndr/metrics/confusion.py
streamndr/metrics/err_rate.py
streamndr/metrics/f_new.py
streamndr/metrics/m_new.py
streamndr/metrics/ttd.py
streamndr/metrics/unk_rate.py
streamndr/model/__init__.py
streamndr/model/ecsminer.py
streamndr/model/ecsminerwf.py
streamndr/model/minas.py
streamndr/utils/__init__.py
streamndr/utils/cluster_utils.py
streamndr/utils/data_structure.py
streamndr/utils/mcikmeans.py
streamndr-0.1.6.dist-info/LICENSE
streamndr-0.1.6.dist-info/METADATA
streamndr-0.1.6.dist-info/WHEEL
streamndr-0.1.6.dist-info/top_level.txt
streamndr-0.1.6.dist-info/RECORD
