Metadata-Version: 2.1
Name: streamndr
Version: 0.1.6
Summary: Stream Novelty Detection for River
Home-page: https://jgaud.github.io/streamndr/
Author: Jean-Gabriel Gaudreault
Author-email: jean-gabrielgaudreault@outlook.com
License: BSD-3
Classifier: License :: OSI Approved :: BSD License
Classifier: Topic :: Scientific/Engineering :: Artificial Intelligence
Classifier: Programming Language :: Python
Classifier: Programming Language :: Python :: 3
Classifier: Programming Language :: Python :: 3.9
Classifier: Programming Language :: Python :: 3.10
Classifier: Programming Language :: Python :: Implementation :: PyPy
Requires-Python: >=3.9.0
License-File: LICENSE
Requires-Dist: scikit-learn >=1.2.1
Requires-Dist: pandas >=1.4.2
Requires-Dist: numpy >=1.23.5
Requires-Dist: river >=0.21.0
Requires-Dist: clusopt-core >=1.0.0
